setup.py
jetpack/__init__.py
jetpack/core.py
jetpack/ui.py
jetpack/version.py
jetpack.egg-info/PKG-INFO
jetpack.egg-info/SOURCES.txt
jetpack.egg-info/dependency_links.txt
jetpack.egg-info/requires.txt
jetpack.egg-info/top_level.txt
scripts/jetpack