Metadata-Version: 1.1
Name: jetpack
Version: 0.8.3
Summary: A package templating system.
Home-page: https://github.com/bmweiner/jetpack
Author: Benjamin Weiner
Author-email: bmweiner@users.noreply.github.com
License: UNKNOWN
Platform: py27
Platform: py35
Classifier: Topic :: Software Development :: Libraries :: Python Modules
Classifier: Natural Language :: English
Classifier: Operating System :: OS Independent
Classifier: Programming Language :: Python
